database_connection_honeycomb/__init__.py
wf_database_connection_honeycomb-0.5.0.dist-info/LICENSE
wf_database_connection_honeycomb-0.5.0.dist-info/METADATA
wf_database_connection_honeycomb-0.5.0.dist-info/WHEEL
wf_database_connection_honeycomb-0.5.0.dist-info/top_level.txt
wf_database_connection_honeycomb-0.5.0.dist-info/RECORD
