Metadata-Version: 2.1
Name: wf-database-connection-honeycomb
Version: 0.5.0
Summary: An implementation of the database_connection API using Wildflower's Honeycomb database
Home-page: https://github.com/WildflowerSchools/database_connection_honeycomb
Author: Theodore Quinn
Author-email: ted.quinn@wildflowerschools.org
License: UNKNOWN
Keywords: database
Platform: UNKNOWN
Classifier: Intended Audience :: Developers
Classifier: License :: OSI Approved :: MIT License
Classifier: Operating System :: OS Independent
Classifier: Programming Language :: Python
Requires-Dist: python-dateutil (>=2.8.0)
Requires-Dist: wf-database-connection (>=0.1.1)
Requires-Dist: wf-minimal-honeycomb-python (>=0.3.0)
